Workbook

Sheet Cover
A1: Budget vs Actual Analysis, Financial Year 2025
A2: Illustrative sportswear company with three product lines. $ thousands unless stated.
A4: Purpose | B4: Compare actual 2025 results with the budget, measure revenue, expense, profit and percentage variances, and explain the major deviations.
A5: Headline | B5: ="Revenue "&TEXT(Summary!E11,"+0.0%;-0.0%")&" vs budget, operating profit "&TEXT(Summary!E26,"+0.0%;-0.0%")&": sold more, made less." -> Revenue +3.2% vs budget, operating profit -2.0%: sold more, made less.
A7: Sheets
A8: Summary | B8: Full-year variance table with materiality flags, and the operating profit bridge with waterfall chart
A9: Commentary | B9: The major deviations, why they happened and what to do
A10: Revenue Analysis | B10: Revenue variance split into price and volume, and revenue mix
A11: Cost Analysis | B11: Cost of sales split into volume and unit-cost effects (flexible budget), and operating expenses
A12: Monthly | B12: Month-by-month variances, year-to-date profit variance and charts
A13: Budget / Actual | B13: Monthly P&L inputs (units, prices, unit costs, expenses)
A14: Checks | B14: Reconciliations; should say OK
A16: Sign convention | B16: Positive variance = favourable (more revenue or less cost than budget). Negative = unfavourable.
A17: Materiality | B17: A line is flagged when its variance is at least 5% and at least $100k (both editable on the Summary sheet, yellow cells).
A18: Colour key | B18: Blue = input, black = formula, green = link to another sheet, yellow = key assumption
A19: Checks status | B19: =Checks!B14 -> OK

Sheet Summary
A1: Budget vs Actual: Full Year 2025
A2: Illustrative sportswear company, $ thousands. Variance is shown so that positive = favourable (better than budget) and negative = unfavourable.
A4: Materiality: flag if |variance %| is at least | E4: 0.05
A5: and |variance| is at least ($k) | E5: 100
A7: $ thousands | B7: Budget | C7: Actual | D7: Variance F/(U) | E7: Variance % | F7: Status
A8: Revenue: Running Shoes | B8: =Budget!N17 -> 23180 | C8: =Actual!N17 -> 23196.15 | D8: =C8-B8 -> 16.15 | E8: =IF(B8=0,0,D8/ABS(B8)) -> 0.00069672131 | F8: =IF(AND(ABS(E8)>=Summary!$E$4,ABS(D8)>=Summary!$E$5),IF(D8>=0,"Favourable: review","Adverse: investigate"),IF(ROUND(D8,0)=0,"On budget",IF(D8>0,"Favourable","Unfavourable"))) -> Favourable
A9: Revenue: Apparel | B9: =Budget!N18 -> 17080 | C9: =Actual!N18 -> 18925.2 | D9: =C9-B9 -> 1845.2 | E9: =IF(B9=0,0,D9/ABS(B9)) -> 0.10803279 | F9: =IF(AND(ABS(E9)>=Summary!$E$4,ABS(D9)>=Summary!$E$5),IF(D9>=0,"Favourable: review","Adverse: investigate"),IF(ROUND(D9,0)=0,"On budget",IF(D9>0,"Favourable","Unfavourable"))) -> Favourable: review
A10: Revenue: Accessories | B10: =Budget!N19 -> 6710 | C10: =Actual!N19 -> 6340.686 | D10: =C10-B10 -> -369.314 | E10: =IF(B10=0,0,D10/ABS(B10)) -> -0.055039344 | F10: =IF(AND(ABS(E10)>=Summary!$E$4,ABS(D10)>=Summary!$E$5),IF(D10>=0,"Favourable: review","Adverse: investigate"),IF(ROUND(D10,0)=0,"On budget",IF(D10>0,"Favourable","Unfavourable"))) -> Adverse: investigate
A11: Total revenue | B11: =Budget!N20 -> 46970 | C11: =Actual!N20 -> 48462.036 | D11: =C11-B11 -> 1492.036 | E11: =IF(B11=0,0,D11/ABS(B11)) -> 0.031765723 | F11: =IF(AND(ABS(E11)>=Summary!$E$4,ABS(D11)>=Summary!$E$5),IF(D11>=0,"Favourable: review","Adverse: investigate"),IF(ROUND(D11,0)=0,"On budget",IF(D11>0,"Favourable","Unfavourable"))) -> Favourable
A12: Cost of sales: Running Shoes | B12: =Budget!N21 -> 10248 | C12: =Actual!N21 -> 10633.115 | D12: =B12-C12 -> -385.1148 | E12: =IF(B12=0,0,D12/ABS(B12)) -> -0.037579508 | F12: =IF(AND(ABS(E12)>=Summary!$E$4,ABS(D12)>=Summary!$E$5),IF(D12>=0,"Favourable: review","Adverse: investigate"),IF(ROUND(D12,0)=0,"On budget",IF(D12>0,"Favourable","Unfavourable"))) -> Unfavourable
A13: Cost of sales: Apparel | B13: =Budget!N22 -> 7259 | C13: =Actual!N22 -> 8043.21 | D13: =B13-C13 -> -784.21 | E13: =IF(B13=0,0,D13/ABS(B13)) -> -0.10803279 | F13: =IF(AND(ABS(E13)>=Summary!$E$4,ABS(D13)>=Summary!$E$5),IF(D13>=0,"Favourable: review","Adverse: investigate"),IF(ROUND(D13,0)=0,"On budget",IF(D13>0,"Favourable","Unfavourable"))) -> Adverse: investigate
A14: Cost of sales: Accessories | B14: =Budget!N23 -> 2440 | C14: =Actual!N23 -> 2416.32 | D14: =B14-C14 -> 23.68 | E14: =IF(B14=0,0,D14/ABS(B14)) -> 0.009704918 | F14: =IF(AND(ABS(E14)>=Summary!$E$4,ABS(D14)>=Summary!$E$5),IF(D14>=0,"Favourable: review","Adverse: investigate"),IF(ROUND(D14,0)=0,"On budget",IF(D14>0,"Favourable","Unfavourable"))) -> Favourable
A15: Total cost of sales | B15: =Budget!N24 -> 19947 | C15: =Actual!N24 -> 21092.645 | D15: =B15-C15 -> -1145.6448 | E15: =IF(B15=0,0,D15/ABS(B15)) -> -0.057434441 | F15: =IF(AND(ABS(E15)>=Summary!$E$4,ABS(D15)>=Summary!$E$5),IF(D15>=0,"Favourable: review","Adverse: investigate"),IF(ROUND(D15,0)=0,"On budget",IF(D15>0,"Favourable","Unfavourable"))) -> Adverse: investigate
A16: Gross profit | B16: =Budget!N25 -> 27023 | C16: =Actual!N25 -> 27369.391 | D16: =C16-B16 -> 346.3912 | E16: =IF(B16=0,0,D16/ABS(B16)) -> 0.012818384 | F16: =IF(AND(ABS(E16)>=Summary!$E$4,ABS(D16)>=Summary!$E$5),IF(D16>=0,"Favourable: review","Adverse: investigate"),IF(ROUND(D16,0)=0,"On budget",IF(D16>0,"Favourable","Unfavourable"))) -> Favourable
A17: Gross margin % | B17: =Budget!N26 -> 0.57532468 | C17: =Actual!N26 -> 0.56475942 | D17: =(C17-B17)*100 -> -1.0565258
A18: Marketing | B18: =Budget!N28 -> 2806 | C18: =Actual!N28 -> 3095.3 | D18: =B18-C18 -> -289.3 | E18: =IF(B18=0,0,D18/ABS(B18)) -> -0.1031005 | F18: =IF(AND(ABS(E18)>=Summary!$E$4,ABS(D18)>=Summary!$E$5),IF(D18>=0,"Favourable: review","Adverse: investigate"),IF(ROUND(D18,0)=0,"On budget",IF(D18>0,"Favourable","Unfavourable"))) -> Adverse: investigate
A19: Salaries and benefits | B19: =Budget!N29 -> 6240 | C19: =Actual!N29 -> 5910 | D19: =B19-C19 -> 330 | E19: =IF(B19=0,0,D19/ABS(B19)) -> 0.052884615 | F19: =IF(AND(ABS(E19)>=Summary!$E$4,ABS(D19)>=Summary!$E$5),IF(D19>=0,"Favourable: review","Adverse: investigate"),IF(ROUND(D19,0)=0,"On budget",IF(D19>0,"Favourable","Unfavourable"))) -> Favourable: review
A20: Rent and occupancy | B20: =Budget!N30 -> 2160 | C20: =Actual!N30 -> 2160 | D20: =B20-C20 -> 0 | E20: =IF(B20=0,0,D20/ABS(B20)) -> 0 | F20: =IF(AND(ABS(E20)>=Summary!$E$4,ABS(D20)>=Summary!$E$5),IF(D20>=0,"Favourable: review","Adverse: investigate"),IF(ROUND(D20,0)=0,"On budget",IF(D20>0,"Favourable","Unfavourable"))) -> On budget
A21: Freight and logistics | B21: =Budget!N31 -> 1878.8 | C21: =Actual!N31 -> 2319.5 | D21: =B21-C21 -> -440.7 | E21: =IF(B21=0,0,D21/ABS(B21)) -> -0.23456462 | F21: =IF(AND(ABS(E21)>=Summary!$E$4,ABS(D21)>=Summary!$E$5),IF(D21>=0,"Favourable: review","Adverse: investigate"),IF(ROUND(D21,0)=0,"On budget",IF(D21>0,"Favourable","Unfavourable"))) -> Adverse: investigate
A22: IT and software | B22: =Budget!N32 -> 720 | C22: =Actual!N32 -> 960 | D22: =B22-C22 -> -240 | E22: =IF(B22=0,0,D22/ABS(B22)) -> -0.33333333 | F22: =IF(AND(ABS(E22)>=Summary!$E$4,ABS(D22)>=Summary!$E$5),IF(D22>=0,"Favourable: review","Adverse: investigate"),IF(ROUND(D22,0)=0,"On budget",IF(D22>0,"Favourable","Unfavourable"))) -> Adverse: investigate
A23: Travel | B23: =Budget!N33 -> 300 | C23: =Actual!N33 -> 260.4 | D23: =B23-C23 -> 39.6 | E23: =IF(B23=0,0,D23/ABS(B23)) -> 0.132 | F23: =IF(AND(ABS(E23)>=Summary!$E$4,ABS(D23)>=Summary!$E$5),IF(D23>=0,"Favourable: review","Adverse: investigate"),IF(ROUND(D23,0)=0,"On budget",IF(D23>0,"Favourable","Unfavourable"))) -> Favourable
A24: Other admin | B24: =Budget!N34 -> 840 | C24: =Actual!N34 -> 831.2 | D24: =B24-C24 -> 8.8 | E24: =IF(B24=0,0,D24/ABS(B24)) -> 0.01047619 | F24: =IF(AND(ABS(E24)>=Summary!$E$4,ABS(D24)>=Summary!$E$5),IF(D24>=0,"Favourable: review","Adverse: investigate"),IF(ROUND(D24,0)=0,"On budget",IF(D24>0,"Favourable","Unfavourable"))) -> Favourable
A25: Total operating expenses | B25: =Budget!N35 -> 14944.8 | C25: =Actual!N35 -> 15536.4 | D25: =B25-C25 -> -591.6 | E25: =IF(B25=0,0,D25/ABS(B25)) -> -0.039585675 | F25: =IF(AND(ABS(E25)>=Summary!$E$4,ABS(D25)>=Summary!$E$5),IF(D25>=0,"Favourable: review","Adverse: investigate"),IF(ROUND(D25,0)=0,"On budget",IF(D25>0,"Favourable","Unfavourable"))) -> Unfavourable
A26: Operating profit | B26: =Budget!N36 -> 12078.2 | C26: =Actual!N36 -> 11832.991 | D26: =C26-B26 -> -245.2088 | E26: =IF(B26=0,0,D26/ABS(B26)) -> -0.020301767 | F26: =IF(AND(ABS(E26)>=Summary!$E$4,ABS(D26)>=Summary!$E$5),IF(D26>=0,"Favourable: review","Adverse: investigate"),IF(ROUND(D26,0)=0,"On budget",IF(D26>0,"Favourable","Unfavourable"))) -> Unfavourable
A27: Operating margin % | B27: =Budget!N37 -> 0.25714712 | C27: =Actual!N37 -> 0.24417033 | D27: =(C27-B27)*100 -> -1.2976788
A29: Operating profit bridge: budget to actual
A30: Step | B30: Impact F/(U) | C30: Running total | D30: Chart helper: base | E30: Increase | F30: Decrease
A31: Budget operating profit | B31: =Budget!N36 -> 12078.2 | C31: =B31 -> 12078.2 | D31: 0 | E31: =B31 -> 12078.2 | F31: 0
A32: Sales volume (at budget margin) | B32: =SUMPRODUCT(Actual!B6:M6-Budget!B6:M6,Budget!B7:M7-Budget!B8:M8)+SUMPRODUCT(Actual!B9:M9-Budget!B9:M9,Budget!B10:M10-Budget!B11:M11)+SUMPRODUCT(Actual!B12:M12-Budget!B12:M12,Budget!B13:M13-Budget!B14:M14) -> 1028.56 | C32: =C31+B32 -> 13106.76 | D32: =MIN(C31,C32) -> 12078.2 | E32: =MAX(B32,0) -> 1028.56 | F32: =MAX(-B32,0) -> 0
A33: Selling prices | B33: =SUMPRODUCT(Actual!B7:M7-Budget!B7:M7,Actual!B6:M6)+SUMPRODUCT(Actual!B10:M10-Budget!B10:M10,Actual!B9:M9)+SUMPRODUCT(Actual!B13:M13-Budget!B13:M13,Actual!B12:M12) -> -304.194 | C33: =C32+B33 -> 12802.566 | D33: =MIN(C32,C33) -> 12802.566 | E33: =MAX(B33,0) -> 0 | F33: =MAX(-B33,0) -> 304.194
A34: Product unit costs | B34: =SUMPRODUCT(Budget!B8:M8-Actual!B8:M8,Actual!B6:M6)+SUMPRODUCT(Budget!B11:M11-Actual!B11:M11,Actual!B9:M9)+SUMPRODUCT(Budget!B14:M14-Actual!B14:M14,Actual!B12:M12) -> -377.9748 | C34: =C33+B34 -> 12424.591 | D34: =MIN(C33,C34) -> 12424.591 | E34: =MAX(B34,0) -> 0 | F34: =MAX(-B34,0) -> 377.9748
A35: Marketing | B35: =Budget!N28-Actual!N28 -> -289.3 | C35: =C34+B35 -> 12135.291 | D35: =MIN(C34,C35) -> 12135.291 | E35: =MAX(B35,0) -> 0 | F35: =MAX(-B35,0) -> 289.3
A36: Salaries and benefits | B36: =Budget!N29-Actual!N29 -> 330 | C36: =C35+B36 -> 12465.291 | D36: =MIN(C35,C36) -> 12135.291 | E36: =MAX(B36,0) -> 330 | F36: =MAX(-B36,0) -> 0
A37: Rent and occupancy | B37: =Budget!N30-Actual!N30 -> 0 | C37: =C36+B37 -> 12465.291 | D37: =MIN(C36,C37) -> 12465.291 | E37: =MAX(B37,0) -> 0 | F37: =MAX(-B37,0) -> 0
A38: Freight and logistics | B38: =Budget!N31-Actual!N31 -> -440.7 | C38: =C37+B38 -> 12024.591 | D38: =MIN(C37,C38) -> 12024.591 | E38: =MAX(B38,0) -> 0 | F38: =MAX(-B38,0) -> 440.7
A39: IT and software | B39: =Budget!N32-Actual!N32 -> -240 | C39: =C38+B39 -> 11784.591 | D39: =MIN(C38,C39) -> 11784.591 | E39: =MAX(B39,0) -> 0 | F39: =MAX(-B39,0) -> 240
A40: Travel | B40: =Budget!N33-Actual!N33 -> 39.6 | C40: =C39+B40 -> 11824.191 | D40: =MIN(C39,C40) -> 11784.591 | E40: =MAX(B40,0) -> 39.6 | F40: =MAX(-B40,0) -> 0
A41: Other admin | B41: =Budget!N34-Actual!N34 -> 8.8 | C41: =C40+B41 -> 11832.991 | D41: =MIN(C40,C41) -> 11824.191 | E41: =MAX(B41,0) -> 8.8 | F41: =MAX(-B41,0) -> 0
A42: Actual operating profit | B42: =Actual!N36 -> 11832.991 | C42: =B42 -> 11832.991 | D42: 0 | E42: =B42 -> 11832.991 | F42: 0
A43: Bridge check (should be 0) | B43: =ROUND(C41-B42,2) -> 0

Sheet Commentary
A1: Variance Commentary: the major deviations and why they happened
A2: Amounts link to the analysis sheets, so they update if the data changes. The explanations describe the events built into this illustrative data.
A4: Area | B4: Variance F/(U) $k | C4: Variance % | D4: What happened | E4: Recommended action
A5: Apparel sales volume | B5: ='Revenue Analysis'!J6 -> 1845.2 | C5: ='Revenue Analysis'!D6 -> 0.10803279 | D5: The spring marketing campaign (March to May) lifted Apparel unit sales by about 18% from March to July, and they stayed about 8% above budget for the rest of the year. Apparel added most of the revenue upside. | E5: Keep the campaign format; build the higher Apparel run-rate into next year's budget.
A6: Marketing | B6: =Summary!D18 -> -289.3 | C6: =Summary!E18 -> -0.1031005 | D6: The campaign cost about 40% more than budgeted marketing in March to May. It paid back: Apparel gross margin from the extra volume was well above the extra spend. | E6: Approve campaign spend through a business case so the overspend is planned rather than reported after the event.
A7: Running Shoes unit cost | B7: ='Cost Analysis'!F5 -> -377.9748 | D7: The main footwear supplier raised prices by 6% from June. Selling prices were not changed, so the whole increase came out of margin. | E7: Renegotiate or dual-source; consider a price rise on the next season's range.
A8: Freight and logistics | B8: =Summary!D21 -> -440.7 | C8: =Summary!E21 -> -0.23456462 | D8: Shipping rates rose in the second half, taking freight from 4.0% to about 5.5% of revenue from July. | E8: Lock in contract rates; review whether the budget's 4% of revenue assumption is still realistic.
A9: Accessories selling price | B9: ='Revenue Analysis'!K7 -> -304.194 | C9: ='Revenue Analysis'!G7 -> -0.045778705 | D9: A 15% discount in October to December lifted Accessories volume by only about 5%, so the discount lost more revenue than it gained. | E9: Do not repeat broad discounting; use targeted promotions and measure their uplift.
A10: IT and software | B10: =Summary!D22 -> -240 | C10: =Summary!E22 -> -0.33333333 | D10: A one-off $240k ERP upgrade in September was not in the budget. | E10: One-off: exclude from run-rate. Add a capital projects line to next year's budget.
A11: Salaries and benefits | B11: =Summary!D19 -> 330 | C11: =Summary!E19 -> 0.052884615 | D11: Planned hires were delayed until mid-year, so salaries were below budget from January to June. This is a timing saving, not a lasting one. | E11: Treat as timing; the full cost is in the run-rate from July.
A13: Overall
A14: ="Revenue was "&TEXT(Summary!D11,"#,##0")&"k ("&TEXT(Summary!E11,"0.0%")&") above budget, but operating profit was "&TEXT(-Summary!D26,"#,##0")&"k ("&TEXT(-Summary!E26,"0.0%")&") below budget." -> Revenue was 1,492k (3.2%) above budget, but operating profit was 245k (2.0%) below budget.
A15: ="The company sold more but made less: higher volumes were more than offset by higher unit costs, discounting, freight and one-off IT spend." -> The company sold more but made less: higher volumes were more than offset by higher unit costs, discounting, freight and one-off IT spend.
A16: ="Operating margin fell from "&TEXT(Summary!B27,"0.0%")&" (budget) to "&TEXT(Summary!C27,"0.0%")&". The IT project is one-off and the salary saving was only timing, but the supplier price rise and higher freight rates are likely to continue, so next year needs action on pricing and costs." -> Operating margin fell from 25.7% (budget) to 24.4%. The IT project is one-off and the salary saving was only timing, but the supplier price rise and higher freight rates are likely to continue, so next year needs action on pricing and costs.

Sheet Revenue Analysis
A1: Revenue Analysis: price and volume
A2: Revenue variance split into volume (selling more or fewer units, at budget price) and price (selling at a different price). Positive = favourable.
A4: Product | B4: Budget units (k) | C4: Actual units (k) | D4: Volume % | E4: Budget avg price | F4: Actual avg price | G4: Price % | H4: Budget revenue | I4: Actual revenue | J4: Volume variance | K4: Price variance | L4: Total variance | M4: Check
A5: Running Shoes | B5: =Budget!N6 -> 244 | C5: =Actual!N6 -> 244.17 | D5: =C5/B5-1 -> 0.00069672131 | E5: =Budget!N7 -> 95 | F5: =Actual!N7 -> 95 | G5: =F5/E5-1 -> 0 | H5: =Budget!N17 -> 23180 | I5: =Actual!N17 -> 23196.15 | J5: =SUMPRODUCT(Actual!B6:M6-Budget!B6:M6,Budget!B7:M7) -> 16.15 | K5: =SUMPRODUCT(Actual!B7:M7-Budget!B7:M7,Actual!B6:M6) -> 0 | L5: =J5+K5 -> 16.15 | M5: =ROUND(L5-(I5-H5),2) -> 0
A6: Apparel | B6: =Budget!N9 -> 427 | C6: =Actual!N9 -> 473.13 | D6: =C6/B6-1 -> 0.10803279 | E6: =Budget!N10 -> 40 | F6: =Actual!N10 -> 40 | G6: =F6/E6-1 -> 0 | H6: =Budget!N18 -> 17080 | I6: =Actual!N18 -> 18925.2 | J6: =SUMPRODUCT(Actual!B9:M9-Budget!B9:M9,Budget!B10:M10) -> 1845.2 | K6: =SUMPRODUCT(Actual!B10:M10-Budget!B10:M10,Actual!B9:M9) -> 0 | L6: =J6+K6 -> 1845.2 | M6: =ROUND(L6-(I6-H6),2) -> 0
A7: Accessories | B7: =Budget!N12 -> 305 | C7: =Actual!N12 -> 302.04 | D7: =C7/B7-1 -> -0.009704918 | E7: =Budget!N13 -> 22 | F7: =Actual!N13 -> 20.992868 | G7: =F7/E7-1 -> -0.045778705 | H7: =Budget!N19 -> 6710 | I7: =Actual!N19 -> 6340.686 | J7: =SUMPRODUCT(Actual!B12:M12-Budget!B12:M12,Budget!B13:M13) -> -65.12 | K7: =SUMPRODUCT(Actual!B13:M13-Budget!B13:M13,Actual!B12:M12) -> -304.194 | L7: =J7+K7 -> -369.314 | M7: =ROUND(L7-(I7-H7),2) -> 0
A8: Total | B8: =SUM(B5:B7) -> 976 | C8: =SUM(C5:C7) -> 1019.34 | D8: =C8/B8-1 -> 0.044405738 | H8: =SUM(H5:H7) -> 46970 | I8: =SUM(I5:I7) -> 48462.036 | J8: =SUM(J5:J7) -> 1796.23 | K8: =SUM(K5:K7) -> -304.194 | L8: =SUM(L5:L7) -> 1492.036 | M8: =SUM(M5:M7) -> 0
A10: Volume variance = (actual units - budget units) x budget price. Price variance = (actual price - budget price) x actual units. Both are calculated month by month and added up.
A12: Revenue mix
A13: Product | B13: Budget mix | C13: Actual mix | D13: Change (pts)
A14: Running Shoes | B14: =H5/H8 -> 0.49350649 | C14: =I5/I8 -> 0.4786458 | D14: =(C14-B14)*100 -> -1.4860693
A15: Apparel | B15: =H6/H8 -> 0.36363636 | C15: =I6/I8 -> 0.39051599 | D15: =(C15-B15)*100 -> 2.6879627
A16: Accessories | B16: =H7/H8 -> 0.14285714 | C16: =I7/I8 -> 0.13083821 | D16: =(C16-B16)*100 -> -1.2018934

Sheet Cost Analysis
A1: Cost Analysis
A2: Cost of sales split into volume and unit-cost effects, a flexible budget, and operating expenses. Positive = favourable (spent less than budget).
A4: Cost of sales | B4: Budget | C4: Flexed budget (actual units at budget cost) | D4: Actual | E4: Volume effect F/(U) | F4: Unit cost effect F/(U) | G4: Total variance F/(U) | H4: Check
A5: Running Shoes | B5: =Budget!N21 -> 10248 | C5: =SUMPRODUCT(Actual!B6:M6,Budget!B8:M8) -> 10255.14 | D5: =Actual!N21 -> 10633.115 | E5: =B5-C5 -> -7.14 | F5: =C5-D5 -> -377.9748 | G5: =E5+F5 -> -385.1148 | H5: =ROUND(G5-(B5-D5),2) -> 0
A6: Apparel | B6: =Budget!N22 -> 7259 | C6: =SUMPRODUCT(Actual!B9:M9,Budget!B11:M11) -> 8043.21 | D6: =Actual!N22 -> 8043.21 | E6: =B6-C6 -> -784.21 | F6: =C6-D6 -> 0 | G6: =E6+F6 -> -784.21 | H6: =ROUND(G6-(B6-D6),2) -> 0
A7: Accessories | B7: =Budget!N23 -> 2440 | C7: =SUMPRODUCT(Actual!B12:M12,Budget!B14:M14) -> 2416.32 | D7: =Actual!N23 -> 2416.32 | E7: =B7-C7 -> 23.68 | F7: =C7-D7 -> 0 | G7: =E7+F7 -> 23.68 | H7: =ROUND(G7-(B7-D7),2) -> 0
A8: Total cost of sales | B8: =SUM(B5:B7) -> 19947 | C8: =SUM(C5:C7) -> 20714.67 | D8: =SUM(D5:D7) -> 21092.645 | E8: =SUM(E5:E7) -> -767.67 | F8: =SUM(F5:F7) -> -377.9748 | G8: =SUM(G5:G7) -> -1145.6448 | H8: =SUM(H5:H7) -> 0
A9: The volume effect is not a real overspend: selling more units costs more. The unit cost effect is the true cost overrun (actual units x (actual cost - budget cost)).
A11: Operating expenses
A12: Expense | B12: Budget | C12: Actual | D12: Variance F/(U) | E12: Variance % | F12: Budget % of revenue | G12: Actual % of revenue | H12: Status
A13: Marketing | B13: =Budget!N28 -> 2806 | C13: =Actual!N28 -> 3095.3 | D13: =B13-C13 -> -289.3 | E13: =D13/B13 -> -0.1031005 | F13: =B13/Budget!N20 -> 0.05974026 | G13: =C13/Actual!N20 -> 0.063870614 | H13: =Summary!F18 -> Adverse: investigate
A14: Salaries and benefits | B14: =Budget!N29 -> 6240 | C14: =Actual!N29 -> 5910 | D14: =B14-C14 -> 330 | E14: =D14/B14 -> 0.052884615 | F14: =B14/Budget!N20 -> 0.13285076 | G14: =C14/Actual!N20 -> 0.12195113 | H14: =Summary!F19 -> Favourable: review
A15: Rent and occupancy | B15: =Budget!N30 -> 2160 | C15: =Actual!N30 -> 2160 | D15: =B15-C15 -> 0 | E15: =D15/B15 -> 0 | F15: =B15/Budget!N20 -> 0.0459868 | G15: =C15/Actual!N20 -> 0.044570971 | H15: =Summary!F20 -> On budget
A16: Freight and logistics | B16: =Budget!N31 -> 1878.8 | C16: =Actual!N31 -> 2319.5 | D16: =B16-C16 -> -440.7 | E16: =D16/B16 -> -0.23456462 | F16: =B16/Budget!N20 -> 0.04 | G16: =C16/Actual!N20 -> 0.047862207 | H16: =Summary!F21 -> Adverse: investigate
A17: IT and software | B17: =Budget!N32 -> 720 | C17: =Actual!N32 -> 960 | D17: =B17-C17 -> -240 | E17: =D17/B17 -> -0.33333333 | F17: =B17/Budget!N20 -> 0.015328933 | G17: =C17/Actual!N20 -> 0.01980932 | H17: =Summary!F22 -> Adverse: investigate
A18: Travel | B18: =Budget!N33 -> 300 | C18: =Actual!N33 -> 260.4 | D18: =B18-C18 -> 39.6 | E18: =D18/B18 -> 0.132 | F18: =B18/Budget!N20 -> 0.0063870556 | G18: =C18/Actual!N20 -> 0.0053732782 | H18: =Summary!F23 -> Favourable
A19: Other admin | B19: =Budget!N34 -> 840 | C19: =Actual!N34 -> 831.2 | D19: =B19-C19 -> 8.8 | E19: =D19/B19 -> 0.01047619 | F19: =B19/Budget!N20 -> 0.017883756 | G19: =C19/Actual!N20 -> 0.01715157 | H19: =Summary!F24 -> Favourable
A20: Total operating expenses | B20: =Budget!N35 -> 14944.8 | C20: =Actual!N35 -> 15536.4 | D20: =B20-C20 -> -591.6 | E20: =D20/B20 -> -0.039585675 | F20: =B20/Budget!N20 -> 0.31817756 | G20: =C20/Actual!N20 -> 0.32058909 | H20: =Summary!F25 -> Unfavourable

Sheet Monthly
A1: Monthly Variance Trend
A2: Monthly budget vs actual, $ thousands. Positive variance = favourable.
A4: $ thousands | B4: Jan | C4: Feb | D4: Mar | E4: Apr | F4: May | G4: Jun | H4: Jul | I4: Aug | J4: Sep | K4: Oct | L4: Nov | M4: Dec | N4: FY 2025
A5: Budget revenue | B5: =Budget!B20 -> 3272.5 | C5: =Budget!C20 -> 3272.5 | D5: =Budget!D20 -> 3657.5 | E5: =Budget!E20 -> 3850 | F5: =Budget!F20 -> 4042.5 | G5: =Budget!G20 -> 4042.5 | H5: =Budget!H20 -> 3850 | I5: =Budget!I20 -> 3850 | ... N5: =Budget!N20 -> 46970
A6: Actual revenue | B6: =Actual!B20 -> 3233.08 | C6: =Actual!C20 -> 3221.96 | D6: =Actual!D20 -> 3888.48 | E6: =Actual!E20 -> 4122.7 | F6: =Actual!F20 -> 4295.7 | G6: =Actual!G20 -> 4295.15 | H6: =Actual!H20 -> 4016.67 | I6: =Actual!I20 -> 3945.17 | ... N6: =Actual!N20 -> 48462.036
A7: Revenue variance F/(U) | B7: =B6-B5 -> -39.42 | C7: =C6-C5 -> -50.54 | D7: =D6-D5 -> 230.98 | E7: =E6-E5 -> 272.7 | F7: =F6-F5 -> 253.2 | G7: =G6-G5 -> 252.65 | H7: =H6-H5 -> 166.67 | I7: =I6-I5 -> 95.17 | ... N7: =N6-N5 -> 1492.036
A8: Revenue variance % | B8: =B7/B5 -> -0.012045837 | C8: =C7/C5 -> -0.01544385 | D8: =D7/D5 -> 0.063152427 | E8: =E7/E5 -> 0.070831169 | F8: =F7/F5 -> 0.062634508 | G8: =G7/G5 -> 0.062498454 | H8: =H7/H5 -> 0.043290909 | I8: =I7/I5 -> 0.024719481 | ... N8: =N7/N5 -> 0.031765723
A10: Budget operating expenses | B10: =Budget!B35 -> 1181.4 | C10: =Budget!C35 -> 1181.4 | D10: =Budget!D35 -> 1219.8 | E10: =Budget!E35 -> 1239 | F10: =Budget!F35 -> 1258.2 | G10: =Budget!G35 -> 1258.2 | H10: =Budget!H35 -> 1239 | I10: =Budget!I35 -> 1239 | ... N10: =Budget!N35 -> 14944.8
A11: Actual operating expenses | B11: =Actual!B35 -> 1120.9 | C11: =Actual!C35 -> 1121 | D11: =Actual!D35 -> 1263.1 | E11: =Actual!E35 -> 1287.4 | F11: =Actual!F35 -> 1309 | G11: =Actual!G35 -> 1217 | H11: =Actual!H35 -> 1298.7 | I11: =Actual!I35 -> 1296.9 | ... N11: =Actual!N35 -> 15536.4
A12: Opex variance F/(U) | B12: =B10-B11 -> 60.5 | C12: =C10-C11 -> 60.4 | D12: =D10-D11 -> -43.3 | E12: =E10-E11 -> -48.4 | F12: =F10-F11 -> -50.8 | G12: =G10-G11 -> 41.2 | H12: =H10-H11 -> -59.7 | I12: =I10-I11 -> -57.9 | ... N12: =N10-N11 -> -591.6
A14: Budget operating profit | B14: =Budget!B36 -> 701.35 | C14: =Budget!C36 -> 701.35 | D14: =Budget!D36 -> 884.45 | E14: =Budget!E36 -> 976 | F14: =Budget!F36 -> 1067.55 | G14: =Budget!G36 -> 1067.55 | H14: =Budget!H36 -> 976 | I14: =Budget!I36 -> 976 | ... N14: =Budget!N36 -> 12078.2
A15: Actual operating profit | B15: =Actual!B36 -> 738.69 | C15: =Actual!C36 -> 731.8 | D15: =Actual!D36 -> 972.63 | E15: =Actual!E36 -> 1082.67 | F15: =Actual!F36 -> 1160.3 | G15: =Actual!G36 -> 1199.0396 | H15: =Actual!H36 -> 961.782 | I15: =Actual!I36 -> 920.8636 | ... N15: =Actual!N36 -> 11832.991
A16: Operating profit variance F/(U) | B16: =B15-B14 -> 37.34 | C16: =C15-C14 -> 30.45 | D16: =D15-D14 -> 88.18 | E16: =E15-E14 -> 106.67 | F16: =F15-F14 -> 92.75 | G16: =G15-G14 -> 131.4896 | H16: =H15-H14 -> -14.218 | I16: =I15-I14 -> -55.1364 | ... N16: =N15-N14 -> -245.2088
A17: Cumulative (YTD) profit variance | B17: =B16 -> 37.34 | C17: =B17+C16 -> 67.79 | D17: =C17+D16 -> 155.97 | E17: =D17+E16 -> 262.64 | F17: =E17+F16 -> 355.39 | G17: =F17+G16 -> 486.8796 | H17: =G17+H16 -> 472.6616 | I17: =H17+I16 -> 417.5252 | J17: =I17+J16 -> 131.494 | ... M17: =L17+M16 -> -245.2088 | N17: =M17 -> -245.2088
A18: Budget gross margin % | B18: =Budget!B26 -> 0.57532468 | C18: =Budget!C26 -> 0.57532468 | D18: =Budget!D26 -> 0.57532468 | E18: =Budget!E26 -> 0.57532468 | F18: =Budget!F26 -> 0.57532468 | G18: =Budget!G26 -> 0.57532468 | H18: =Budget!H26 -> 0.57532468 | I18: =Budget!I26 -> 0.57532468 | ... N18: =Budget!N26 -> 0.57532468
A19: Actual gross margin % | B19: =Actual!B26 -> 0.57517599 | C19: =Actual!C26 -> 0.57505369 | D19: =Actual!D26 -> 0.57496245 | E19: =Actual!E26 -> 0.57488297 | F19: =Actual!F26 -> 0.57483064 | G19: =Actual!G26 -> 0.56250413 | H19: =Actual!H26 -> 0.56277513 | I19: =Actual!I26 -> 0.56214652 | ... N19: =Actual!N26 -> 0.56475942
A21: Chart helper: favourable | B21: =MAX(B16,0) -> 37.34 | C21: =MAX(C16,0) -> 30.45 | D21: =MAX(D16,0) -> 88.18 | E21: =MAX(E16,0) -> 106.67 | F21: =MAX(F16,0) -> 92.75 | G21: =MAX(G16,0) -> 131.4896 | H21: =MAX(H16,0) -> 0 | I21: =MAX(I16,0) -> 0 | ... M21: =MAX(M16,0) -> 0
A22: Chart helper: unfavourable | B22: =MIN(B16,0) -> 0 | C22: =MIN(C16,0) -> 0 | D22: =MIN(D16,0) -> 0 | E22: =MIN(E16,0) -> 0 | F22: =MIN(F16,0) -> 0 | G22: =MIN(G16,0) -> 0 | H22: =MIN(H16,0) -> -14.218 | I22: =MIN(I16,0) -> -55.1364 | ... M22: =MIN(M16,0) -> -148.606

Sheet Budget
A1: Budget: monthly P&L, 2025
A2: Units in thousands, prices and unit costs in $, all other amounts in $ thousands. Blue = input.
A4: $ thousands | B4: Jan | C4: Feb | D4: Mar | E4: Apr | F4: May | G4: Jun | H4: Jul | I4: Aug | J4: Sep | K4: Oct | L4: Nov | M4: Dec | N4: FY 2025
A5: Volumes, prices and unit costs
A6: Running Shoes units (k) | B6: 17 | C6: 17 | D6: 19 | E6: 20 | F6: 21 | G6: 21 | H6: 20 | I6: 20 | J6: 19 | K6: 20 | L6: 23 | M6: 27 | N6: =SUM(B6:M6) -> 244
A7: Running Shoes selling price ($) | B7: 95 | C7: 95 | D7: 95 | E7: 95 | F7: 95 | G7: 95 | H7: 95 | I7: 95 | J7: 95 | K7: 95 | L7: 95 | M7: 95 | N7: =N17/N6 -> 95
A8: Running Shoes unit cost ($) | B8: 42 | C8: 42 | D8: 42 | E8: 42 | F8: 42 | G8: 42 | H8: 42 | I8: 42 | J8: 42 | K8: 42 | L8: 42 | M8: 42 | N8: =N21/N6 -> 42
A9: Apparel units (k) | B9: 29.75 | C9: 29.75 | D9: 33.25 | E9: 35 | F9: 36.75 | G9: 36.75 | H9: 35 | I9: 35 | J9: 33.25 | K9: 35 | L9: 40.25 | M9: 47.25 | N9: =SUM(B9:M9) -> 427
A10: Apparel selling price ($) | B10: 40 | C10: 40 | D10: 40 | E10: 40 | F10: 40 | G10: 40 | H10: 40 | I10: 40 | J10: 40 | K10: 40 | L10: 40 | M10: 40 | N10: =N18/N9 -> 40
A11: Apparel unit cost ($) | B11: 17 | C11: 17 | D11: 17 | E11: 17 | F11: 17 | G11: 17 | H11: 17 | I11: 17 | J11: 17 | K11: 17 | L11: 17 | M11: 17 | N11: =N22/N9 -> 17
A12: Accessories units (k) | B12: 21.25 | C12: 21.25 | D12: 23.75 | E12: 25 | F12: 26.25 | G12: 26.25 | H12: 25 | I12: 25 | J12: 23.75 | K12: 25 | L12: 28.75 | M12: 33.75 | N12: =SUM(B12:M12) -> 305
A13: Accessories selling price ($) | B13: 22 | C13: 22 | D13: 22 | E13: 22 | F13: 22 | G13: 22 | H13: 22 | I13: 22 | J13: 22 | K13: 22 | L13: 22 | M13: 22 | N13: =N19/N12 -> 22
A14: Accessories unit cost ($) | B14: 8 | C14: 8 | D14: 8 | E14: 8 | F14: 8 | G14: 8 | H14: 8 | I14: 8 | J14: 8 | K14: 8 | L14: 8 | M14: 8 | N14: =N23/N12 -> 8
A16: Income statement
A17: Revenue: Running Shoes | B17: =B6*B7 -> 1615 | C17: =C6*C7 -> 1615 | D17: =D6*D7 -> 1805 | E17: =E6*E7 -> 1900 | F17: =F6*F7 -> 1995 | G17: =G6*G7 -> 1995 | H17: =H6*H7 -> 1900 | I17: =I6*I7 -> 1900 | ... M17: =M6*M7 -> 2565 | N17: =SUM(B17:M17) -> 23180
A18: Revenue: Apparel | B18: =B9*B10 -> 1190 | C18: =C9*C10 -> 1190 | D18: =D9*D10 -> 1330 | E18: =E9*E10 -> 1400 | F18: =F9*F10 -> 1470 | G18: =G9*G10 -> 1470 | H18: =H9*H10 -> 1400 | I18: =I9*I10 -> 1400 | ... M18: =M9*M10 -> 1890 | N18: =SUM(B18:M18) -> 17080
A19: Revenue: Accessories | B19: =B12*B13 -> 467.5 | C19: =C12*C13 -> 467.5 | D19: =D12*D13 -> 522.5 | E19: =E12*E13 -> 550 | F19: =F12*F13 -> 577.5 | G19: =G12*G13 -> 577.5 | H19: =H12*H13 -> 550 | I19: =I12*I13 -> 550 | ... M19: =M12*M13 -> 742.5 | N19: =SUM(B19:M19) -> 6710
A20: Total revenue | B20: =SUM(B17:B19) -> 3272.5 | C20: =SUM(C17:C19) -> 3272.5 | D20: =SUM(D17:D19) -> 3657.5 | E20: =SUM(E17:E19) -> 3850 | F20: =SUM(F17:F19) -> 4042.5 | G20: =SUM(G17:G19) -> 4042.5 | H20: =SUM(H17:H19) -> 3850 | I20: =SUM(I17:I19) -> 3850 | ... N20: =SUM(N17:N19) -> 46970
A21: Cost of sales: Running Shoes | B21: =B6*B8 -> 714 | C21: =C6*C8 -> 714 | D21: =D6*D8 -> 798 | E21: =E6*E8 -> 840 | F21: =F6*F8 -> 882 | G21: =G6*G8 -> 882 | H21: =H6*H8 -> 840 | I21: =I6*I8 -> 840 | ... M21: =M6*M8 -> 1134 | N21: =SUM(B21:M21) -> 10248
A22: Cost of sales: Apparel | B22: =B9*B11 -> 505.75 | C22: =C9*C11 -> 505.75 | D22: =D9*D11 -> 565.25 | E22: =E9*E11 -> 595 | F22: =F9*F11 -> 624.75 | G22: =G9*G11 -> 624.75 | H22: =H9*H11 -> 595 | I22: =I9*I11 -> 595 | ... M22: =M9*M11 -> 803.25 | N22: =SUM(B22:M22) -> 7259
A23: Cost of sales: Accessories | B23: =B12*B14 -> 170 | C23: =C12*C14 -> 170 | D23: =D12*D14 -> 190 | E23: =E12*E14 -> 200 | F23: =F12*F14 -> 210 | G23: =G12*G14 -> 210 | H23: =H12*H14 -> 200 | I23: =I12*I14 -> 200 | ... M23: =M12*M14 -> 270 | N23: =SUM(B23:M23) -> 2440
A24: Total cost of sales | B24: =SUM(B21:B23) -> 1389.75 | C24: =SUM(C21:C23) -> 1389.75 | D24: =SUM(D21:D23) -> 1553.25 | E24: =SUM(E21:E23) -> 1635 | F24: =SUM(F21:F23) -> 1716.75 | G24: =SUM(G21:G23) -> 1716.75 | H24: =SUM(H21:H23) -> 1635 | I24: =SUM(I21:I23) -> 1635 | ... N24: =SUM(N21:N23) -> 19947
A25: Gross profit | B25: =B20-B24 -> 1882.75 | C25: =C20-C24 -> 1882.75 | D25: =D20-D24 -> 2104.25 | E25: =E20-E24 -> 2215 | F25: =F20-F24 -> 2325.75 | G25: =G20-G24 -> 2325.75 | H25: =H20-H24 -> 2215 | I25: =I20-I24 -> 2215 | ... N25: =N20-N24 -> 27023
A26: Gross margin % | B26: =B25/B20 -> 0.57532468 | C26: =C25/C20 -> 0.57532468 | D26: =D25/D20 -> 0.57532468 | E26: =E25/E20 -> 0.57532468 | F26: =F25/F20 -> 0.57532468 | G26: =G25/G20 -> 0.57532468 | H26: =H25/H20 -> 0.57532468 | I26: =I25/I20 -> 0.57532468 | ... N26: =N25/N20 -> 0.57532468
A28: Marketing | B28: 195.5 | C28: 195.5 | D28: 218.5 | E28: 230 | F28: 241.5 | G28: 241.5 | H28: 230 | I28: 230 | J28: 218.5 | K28: 230 | L28: 264.5 | M28: 310.5 | N28: =SUM(B28:M28) -> 2806
A29: Salaries and benefits | B29: 520 | C29: 520 | D29: 520 | E29: 520 | F29: 520 | G29: 520 | H29: 520 | I29: 520 | J29: 520 | K29: 520 | L29: 520 | M29: 520 | N29: =SUM(B29:M29) -> 6240
A30: Rent and occupancy | B30: 180 | C30: 180 | D30: 180 | E30: 180 | F30: 180 | G30: 180 | H30: 180 | I30: 180 | J30: 180 | K30: 180 | L30: 180 | M30: 180 | N30: =SUM(B30:M30) -> 2160
A31: Freight and logistics | B31: 130.9 | C31: 130.9 | D31: 146.3 | E31: 154 | F31: 161.7 | G31: 161.7 | H31: 154 | I31: 154 | J31: 146.3 | K31: 154 | L31: 177.1 | M31: 207.9 | N31: =SUM(B31:M31) -> 1878.8
A32: IT and software | B32: 60 | C32: 60 | D32: 60 | E32: 60 | F32: 60 | G32: 60 | H32: 60 | I32: 60 | J32: 60 | K32: 60 | L32: 60 | M32: 60 | N32: =SUM(B32:M32) -> 720
A33: Travel | B33: 25 | C33: 25 | D33: 25 | E33: 25 | F33: 25 | G33: 25 | H33: 25 | I33: 25 | J33: 25 | K33: 25 | L33: 25 | M33: 25 | N33: =SUM(B33:M33) -> 300
A34: Other admin | B34: 70 | C34: 70 | D34: 70 | E34: 70 | F34: 70 | G34: 70 | H34: 70 | I34: 70 | J34: 70 | K34: 70 | L34: 70 | M34: 70 | N34: =SUM(B34:M34) -> 840
A35: Total operating expenses | B35: =SUM(B28:B34) -> 1181.4 | C35: =SUM(C28:C34) -> 1181.4 | D35: =SUM(D28:D34) -> 1219.8 | E35: =SUM(E28:E34) -> 1239 | F35: =SUM(F28:F34) -> 1258.2 | G35: =SUM(G28:G34) -> 1258.2 | H35: =SUM(H28:H34) -> 1239 | I35: =SUM(I28:I34) -> 1239 | ... N35: =SUM(N28:N34) -> 14944.8
A36: Operating profit | B36: =B25-B35 -> 701.35 | C36: =C25-C35 -> 701.35 | D36: =D25-D35 -> 884.45 | E36: =E25-E35 -> 976 | F36: =F25-F35 -> 1067.55 | G36: =G25-G35 -> 1067.55 | H36: =H25-H35 -> 976 | I36: =I25-I35 -> 976 | ... N36: =N25-N35 -> 12078.2
A37: Operating margin % | B37: =B36/B20 -> 0.21431627 | C37: =C36/C20 -> 0.21431627 | D37: =D36/D20 -> 0.24181818 | E37: =E36/E20 -> 0.25350649 | F37: =F36/F20 -> 0.26408163 | G37: =G36/G20 -> 0.26408163 | H37: =H36/H20 -> 0.25350649 | I37: =I36/I20 -> 0.25350649 | ... N37: =N36/N20 -> 0.25714712

Sheet Actual
A1: Actual: monthly P&L, 2025
A2: Units in thousands, prices and unit costs in $, all other amounts in $ thousands. Blue = input.
A4: $ thousands | B4: Jan | C4: Feb | D4: Mar | E4: Apr | F4: May | G4: Jun | H4: Jul | I4: Aug | J4: Sep | K4: Oct | L4: Nov | M4: Dec | N4: FY 2025
A5: Volumes, prices and unit costs
A6: Running Shoes units (k) | B6: 16.88 | C6: 16.7 | D6: 18.94 | E6: 20.36 | F6: 21.3 | G6: 21.27 | H6: 19.65 | I6: 20.07 | J6: 19.06 | K6: 19.69 | L6: 23.15 | M6: 27.1 | N6: =SUM(B6:M6) -> 244.17
A7: Running Shoes selling price ($) | B7: 95 | C7: 95 | D7: 95 | E7: 95 | F7: 95 | G7: 95 | H7: 95 | I7: 95 | J7: 95 | K7: 95 | L7: 95 | M7: 95 | N7: =N17/N6 -> 95
A8: Running Shoes unit cost ($) | B8: 42 | C8: 42 | D8: 42 | E8: 42 | F8: 42 | G8: 44.52 | H8: 44.52 | I8: 44.52 | J8: 44.52 | K8: 44.52 | L8: 44.52 | M8: 44.52 | N8: =N21/N6 -> 43.547999
A9: Apparel units (k) | B9: 29.33 | C9: 29.76 | D9: 39.75 | E9: 41.43 | F9: 43 | G9: 42.81 | H9: 40.57 | I9: 37.73 | J9: 35.95 | K9: 37.68 | L9: 43.93 | M9: 51.19 | N9: =SUM(B9:M9) -> 473.13
A10: Apparel selling price ($) | B10: 40 | C10: 40 | D10: 40 | E10: 40 | F10: 40 | G10: 40 | H10: 40 | I10: 40 | J10: 40 | K10: 40 | L10: 40 | M10: 40 | N10: =N18/N9 -> 40
A11: Apparel unit cost ($) | B11: 17 | C11: 17 | D11: 17 | E11: 17 | F11: 17 | G11: 17 | H11: 17 | I11: 17 | J11: 17 | K11: 17 | L11: 17 | M11: 17 | N11: =N22/N9 -> 17
A12: Accessories units (k) | B12: 20.74 | C12: 20.23 | D12: 22.69 | E12: 24.15 | F12: 25.1 | G12: 25.55 | H12: 23.96 | I12: 24.06 | J12: 23.38 | K12: 26.52 | L12: 30.28 | M12: 35.38 | N12: =SUM(B12:M12) -> 302.04
A13: Accessories selling price ($) | B13: 22 | C13: 22 | D13: 22 | E13: 22 | F13: 22 | G13: 22 | H13: 22 | I13: 22 | J13: 22 | K13: 18.7 | L13: 18.7 | M13: 18.7 | N13: =N19/N12 -> 20.992868
A14: Accessories unit cost ($) | B14: 8 | C14: 8 | D14: 8 | E14: 8 | F14: 8 | G14: 8 | H14: 8 | I14: 8 | J14: 8 | K14: 8 | L14: 8 | M14: 8 | N14: =N23/N12 -> 8
A16: Income statement
A17: Revenue: Running Shoes | B17: =B6*B7 -> 1603.6 | C17: =C6*C7 -> 1586.5 | D17: =D6*D7 -> 1799.3 | E17: =E6*E7 -> 1934.2 | F17: =F6*F7 -> 2023.5 | G17: =G6*G7 -> 2020.65 | H17: =H6*H7 -> 1866.75 | I17: =I6*I7 -> 1906.65 | ... M17: =M6*M7 -> 2574.5 | N17: =SUM(B17:M17) -> 23196.15
A18: Revenue: Apparel | B18: =B9*B10 -> 1173.2 | C18: =C9*C10 -> 1190.4 | D18: =D9*D10 -> 1590 | E18: =E9*E10 -> 1657.2 | F18: =F9*F10 -> 1720 | G18: =G9*G10 -> 1712.4 | H18: =H9*H10 -> 1622.8 | I18: =I9*I10 -> 1509.2 | ... M18: =M9*M10 -> 2047.6 | N18: =SUM(B18:M18) -> 18925.2
A19: Revenue: Accessories | B19: =B12*B13 -> 456.28 | C19: =C12*C13 -> 445.06 | D19: =D12*D13 -> 499.18 | E19: =E12*E13 -> 531.3 | F19: =F12*F13 -> 552.2 | G19: =G12*G13 -> 562.1 | H19: =H12*H13 -> 527.12 | I19: =I12*I13 -> 529.32 | ... M19: =M12*M13 -> 661.606 | N19: =SUM(B19:M19) -> 6340.686
A20: Total revenue | B20: =SUM(B17:B19) -> 3233.08 | C20: =SUM(C17:C19) -> 3221.96 | D20: =SUM(D17:D19) -> 3888.48 | E20: =SUM(E17:E19) -> 4122.7 | F20: =SUM(F17:F19) -> 4295.7 | G20: =SUM(G17:G19) -> 4295.15 | H20: =SUM(H17:H19) -> 4016.67 | I20: =SUM(I17:I19) -> 3945.17 | ... N20: =SUM(N17:N19) -> 48462.036
A21: Cost of sales: Running Shoes | B21: =B6*B8 -> 708.96 | C21: =C6*C8 -> 701.4 | D21: =D6*D8 -> 795.48 | E21: =E6*E8 -> 855.12 | F21: =F6*F8 -> 894.6 | G21: =G6*G8 -> 946.9404 | H21: =H6*H8 -> 874.818 | I21: =I6*I8 -> 893.5164 | ... M21: =M6*M8 -> 1206.492 | N21: =SUM(B21:M21) -> 10633.115
A22: Cost of sales: Apparel | B22: =B9*B11 -> 498.61 | C22: =C9*C11 -> 505.92 | D22: =D9*D11 -> 675.75 | E22: =E9*E11 -> 704.31 | F22: =F9*F11 -> 731 | G22: =G9*G11 -> 727.77 | H22: =H9*H11 -> 689.69 | I22: =I9*I11 -> 641.41 | ... M22: =M9*M11 -> 870.23 | N22: =SUM(B22:M22) -> 8043.21
A23: Cost of sales: Accessories | B23: =B12*B14 -> 165.92 | C23: =C12*C14 -> 161.84 | D23: =D12*D14 -> 181.52 | E23: =E12*E14 -> 193.2 | F23: =F12*F14 -> 200.8 | G23: =G12*G14 -> 204.4 | H23: =H12*H14 -> 191.68 | I23: =I12*I14 -> 192.48 | ... M23: =M12*M14 -> 283.04 | N23: =SUM(B23:M23) -> 2416.32
A24: Total cost of sales | B24: =SUM(B21:B23) -> 1373.49 | C24: =SUM(C21:C23) -> 1369.16 | D24: =SUM(D21:D23) -> 1652.75 | E24: =SUM(E21:E23) -> 1752.63 | F24: =SUM(F21:F23) -> 1826.4 | G24: =SUM(G21:G23) -> 1879.1104 | H24: =SUM(H21:H23) -> 1756.188 | I24: =SUM(I21:I23) -> 1727.4064 | ... N24: =SUM(N21:N23) -> 21092.645
A25: Gross profit | B25: =B20-B24 -> 1859.59 | C25: =C20-C24 -> 1852.8 | D25: =D20-D24 -> 2235.73 | E25: =E20-E24 -> 2370.07 | F25: =F20-F24 -> 2469.3 | G25: =G20-G24 -> 2416.0396 | H25: =H20-H24 -> 2260.482 | I25: =I20-I24 -> 2217.7636 | ... N25: =N20-N24 -> 27369.391
A26: Gross margin % | B26: =B25/B20 -> 0.57517599 | C26: =C25/C20 -> 0.57505369 | D26: =D25/D20 -> 0.57496245 | E26: =E25/E20 -> 0.57488297 | F26: =F25/F20 -> 0.57483064 | G26: =G25/G20 -> 0.56250413 | H26: =H25/H20 -> 0.56277513 | I26: =I25/I20 -> 0.56214652 | ... N26: =N25/N20 -> 0.56475942
A28: Marketing | B28: 190.5 | C28: 194.7 | D28: 305.9 | E28: 322 | F28: 338.1 | G28: 243.5 | H28: 232.5 | I28: 234.1 | J28: 221.5 | K28: 225.2 | L28: 270.5 | M28: 316.8 | N28: =SUM(B28:M28) -> 3095.3
A29: Salaries and benefits | B29: 470 | C29: 470 | D29: 470 | E29: 470 | F29: 470 | G29: 470 | H29: 515 | I29: 515 | J29: 515 | K29: 515 | L29: 515 | M29: 515 | N29: =SUM(B29:M29) -> 5910
A30: Rent and occupancy | B30: 180 | C30: 180 | D30: 180 | E30: 180 | F30: 180 | G30: 180 | H30: 180 | I30: 180 | J30: 180 | K30: 180 | L30: 180 | M30: 180 | N30: =SUM(B30:M30) -> 2160
A31: Freight and logistics | B31: 129.3 | C31: 128.9 | D31: 155.5 | E31: 164.9 | F31: 171.8 | G31: 171.8 | H31: 220.9 | I31: 217 | J31: 206.9 | K31: 213.1 | L31: 248.8 | M31: 290.6 | N31: =SUM(B31:M31) -> 2319.5
A32: IT and software | B32: 60 | C32: 60 | D32: 60 | E32: 60 | F32: 60 | G32: 60 | H32: 60 | I32: 60 | J32: 300 | K32: 60 | L32: 60 | M32: 60 | N32: =SUM(B32:M32) -> 960
A33: Travel | B33: 22 | C33: 20.3 | D33: 20.8 | E33: 23.7 | F33: 20.4 | G33: 21.4 | H33: 21.6 | I33: 22.6 | J33: 21.1 | K33: 21.8 | L33: 21.2 | M33: 23.5 | N33: =SUM(B33:M33) -> 260.4
A34: Other admin | B34: 69.1 | C34: 67.1 | D34: 70.9 | E34: 66.8 | F34: 68.7 | G34: 70.3 | H34: 68.7 | I34: 68.2 | J34: 73.4 | K34: 66.8 | L34: 71.4 | M34: 69.8 | N34: =SUM(B34:M34) -> 831.2
A35: Total operating expenses | B35: =SUM(B28:B34) -> 1120.9 | C35: =SUM(C28:C34) -> 1121 | D35: =SUM(D28:D34) -> 1263.1 | E35: =SUM(E28:E34) -> 1287.4 | F35: =SUM(F28:F34) -> 1309 | G35: =SUM(G28:G34) -> 1217 | H35: =SUM(H28:H34) -> 1298.7 | I35: =SUM(I28:I34) -> 1296.9 | ... N35: =SUM(N28:N34) -> 15536.4
A36: Operating profit | B36: =B25-B35 -> 738.69 | C36: =C25-C35 -> 731.8 | D36: =D25-D35 -> 972.63 | E36: =E25-E35 -> 1082.67 | F36: =F25-F35 -> 1160.3 | G36: =G25-G35 -> 1199.0396 | H36: =H25-H35 -> 961.782 | I36: =I25-I35 -> 920.8636 | ... N36: =N25-N35 -> 11832.991
A37: Operating margin % | B37: =B36/B20 -> 0.22847873 | C37: =C36/C20 -> 0.22712883 | D37: =D36/D20 -> 0.25013116 | E37: =E36/E20 -> 0.26261188 | F37: =F36/F20 -> 0.27010732 | G37: =G36/G20 -> 0.27916129 | H37: =H36/H20 -> 0.2394476 | I37: =I36/I20 -> 0.23341544 | ... N37: =N36/N20 -> 0.24417033

Sheet Checks
A1: Checks
A2: Every check should be 0. Data totals are the sums of the raw CSV files.
A4: Check | B4: Difference
A5: Budget revenue agrees to data | B5: =ROUND(Budget!N20-46970,2) -> 0
A6: Actual revenue agrees to data | B6: =ROUND(Actual!N20-48462.036,2) -> 0
A7: Budget opex agrees to data | B7: =ROUND(Budget!N35-14944.8,2) -> 0
A8: Actual opex agrees to data | B8: =ROUND(Actual!N35-15536.4,2) -> 0
A9: Price + volume = revenue variance | B9: ='Revenue Analysis'!M8 -> 0
A10: Volume + unit cost = cost of sales variance | B10: ='Cost Analysis'!H8 -> 0
A11: Profit bridge adds up to actual profit | B11: =Summary!B43 -> 0
A12: Monthly profit variances add up to full year | B12: =ROUND(Monthly!N17-Summary!D26,2) -> 0
A14: Overall status | B14: =IF(SUMPRODUCT(ABS(B5:B12))=0,"OK","ERROR") -> OK
